<?xml version="1.0" encoding="utf-8"?>
<intro>
    <text key="Hint" text="当心那些油桶，它们产生的爆炸是致命的！"/>
    <text key="Hint" text="盟军擅长高精尖科技和精确打击"/>
    <text key="Hint" text="苏联以强大的火力和装甲碾压敌人"/>
    <text key="Hint" text="尤里掌握独特的心灵力量和生物技术"/>
    <text key="Hint" text="超级武器通常需要几分钟的冷却才能再次使用"/>
    <text key="Hint" text="低级防御塔对步兵很有效，而高级防御塔更擅长反载具"/>
    <text key="Hint" text="隐藏的科技钻油井每分钟为你带来20RP的收入"/>
    <text key="Hint" text="重甲坦克可以完全防御部分武器的攻击"/>
    <text key="Hint" text="布甲的子弹抗性高，而铁甲更适合防爆"/>
    <text key="Hint" text="优先对付正在呼叫支援或放置防御塔的敌人"/>
</intro>
